{
  "name": "BB_03_02_ProviderData",
  "nodes": [
    {
      "parameters": {
        "httpMethod": "POST",
        "path": "bb03-provider-data",
        "responseMode": "lastNode",
        "options": {}
      },
      "id": "webhook",
      "name": "\ud83e\uddea Test Webhook",
      "type": "n8n-nodes-base.webhook",
      "typeVersion": 2,
      "position": [
        0,
        300
      ],
      "webhookId": "bb03-provider-data-test"
    },
    {
      "parameters": {
        "inputSource": "passthrough"
      },
      "id": "trigger",
      "name": "Start",
      "type": "n8n-nodes-base.executeWorkflowTrigger",
      "typeVersion": 1.1,
      "position": [
        0,
        500
      ]
    },
    {
      "parameters": {
        "jsCode": "const WORKFLOW_ID = 'BB_03_02_ProviderData';\nconst meta = () => ({ source: 'guard', timestamp: new Date().toISOString(), workflow_id: WORKFLOW_ID });\nconst fail = (code, msg) => [{ json: { success: false, error_code: code, error_message: msg, data: null, _meta: meta() } }];\nconst ok = (data) => [{ json: { success: true, error_code: null, error_message: null, data, _meta: meta() } }];\n\ntry {\n  const items = $input.all();\n  if (!items?.length) return fail('VAL_NO_INPUT', 'No input received');\n\n  const raw = items[0].json.body || items[0].json;\n  \n  if (!raw.provider_slug) {\n    return fail('VAL_MISSING_SLUG', 'Missing provider_slug in input');\n  }\n\n  return ok({\n    provider_slug: String(raw.provider_slug).toLowerCase().trim()\n  });\n} catch (e) {\n  return fail('INTERNAL_ERROR', `${WORKFLOW_ID}: ${e.message}`);\n}"
      },
      "id": "guard",
      "name": "Guard",
      "type": "n8n-nodes-base.code",
      "typeVersion": 2,
      "position": [
        220,
        400
      ]
    },
    {
      "parameters": {
        "conditions": {
          "options": {
            "caseSensitive": true,
            "version": 2
          },
          "conditions": [
            {
              "id": "check-success",
              "leftValue": "={{ $json.success }}",
              "operator": {
                "type": "boolean",
                "operation": "true"
              }
            }
          ],
          "combinator": "and"
        }
      },
      "id": "guard_ok",
      "name": "Guard OK?",
      "type": "n8n-nodes-base.if",
      "typeVersion": 2,
      "position": [
        440,
        400
      ]
    },
    {
      "parameters": {
        "operation": "executeQuery",
        "query": "=SELECT \n  id, name, email, google_calendar_id, \n  slot_duration_mins as slot_duration, \n  min_notice_hours, \n  public_booking_enabled, \n  slug\nFROM public.providers \nWHERE slug = '{{ $json.data.provider_slug }}' \nAND deleted_at IS NULL \nLIMIT 1;"
      },
      "id": "db_get_provider",
      "name": "DB: Get Provider",
      "type": "n8n-nodes-base.postgres",
      "typeVersion": 2.6,
      "position": [
        660,
        300
      ],
      "credentials": {
        "postgres": {
          "id": "99BnrzwZQDhYU6Ly"
        }
      },
      "alwaysOutputData": true,
      "onError": "continueRegularOutput"
    },
    {
      "parameters": {
        "jsCode": "const WORKFLOW_ID = 'BB_03_02_ProviderData';\nconst meta = () => ({ source: 'validate_db', timestamp: new Date().toISOString(), workflow_id: WORKFLOW_ID });\nconst fail = (code, msg) => [{ json: { success: false, error_code: code, error_message: msg, data: null, _meta: meta() } }];\nconst ok = (data) => [{ json: { success: true, error_code: null, error_message: null, data, _meta: meta() } }];\n\ntry {\n  const items = $input.all();\n  const result = items[0].json;\n\n  // Check for DB error (onError=continue case)\n  if (result.error) {\n    return fail('DB_ERROR', `Database failed: ${result.error.message || 'Unknown DB error'}`);\n  }\n\n  // Check if result is empty (alwaysOutputData=true case)\n  if (!result.id) {\n    return fail('PROV_NOT_FOUND', 'Provider not found or inactive');\n  }\n\n  return ok(result);\n} catch (e) {\n  return fail('INTERNAL_ERROR', `${WORKFLOW_ID}: ${e.message}`);\n}"
      },
      "id": "validate_db",
      "name": "Validate DB Result",
      "type": "n8n-nodes-base.code",
      "typeVersion": 2,
      "position": [
        880,
        300
      ]
    },
    {
      "parameters": {
        "conditions": {
          "options": {
            "caseSensitive": true,
            "version": 2
          },
          "conditions": [
            {
              "id": "check-success",
              "leftValue": "={{ $json.success }}",
              "operator": {
                "type": "boolean",
                "operation": "true"
              }
            }
          ],
          "combinator": "and"
        }
      },
      "id": "route_success",
      "name": "Route: Success?",
      "type": "n8n-nodes-base.if",
      "typeVersion": 2,
      "position": [
        1100,
        300
      ]
    },
    {
      "parameters": {
        "jsCode": "const WORKFLOW_ID = 'BB_03_02_ProviderData';\nconst meta = () => ({ source: 'format_output', timestamp: new Date().toISOString(), workflow_id: WORKFLOW_ID });\n\ntry {\n  const raw = $input.first()?.json;\n  // If success=false is already there, pass it through\n  if (raw.success === false) return [ { json: raw } ];\n  \n  return [{ \n    json: {\n      success: true,\n      error_code: null,\n      error_message: null,\n      data: raw.data || raw,\n      _meta: meta()\n    }\n  }];\n} catch (e) {\n  return [{ \n    json: {\n      success: false,\n      error_code: 'INTERNAL_ERROR',\n      error_message: `${WORKFLOW_ID}: ${e.message}`,\n      data: null,\n      _meta: meta()\n    }\n  }];\n}"
      },
      "id": "format_output",
      "name": "Format Output",
      "type": "n8n-nodes-base.code",
      "typeVersion": 2,
      "position": [
        1350,
        400
      ]
    }
  ],
  "connections": {
    "\ud83e\uddea Test Webhook": {
      "main": [
        [
          {
            "node": "Guard",
            "type": "main",
            "index": 0
          }
        ]
      ]
    },
    "Start": {
      "main": [
        [
          {
            "node": "Guard",
            "type": "main",
            "index": 0
          }
        ]
      ]
    },
    "Guard": {
      "main": [
        [
          {
            "node": "Guard OK?",
            "type": "main",
            "index": 0
          }
        ]
      ]
    },
    "Guard OK?": {
      "main": [
        [
          {
            "node": "DB: Get Provider",
            "type": "main",
            "index": 0
          }
        ],
        [
          {
            "node": "Format Output",
            "type": "main",
            "index": 0
          }
        ]
      ]
    },
    "DB: Get Provider": {
      "main": [
        [
          {
            "node": "Validate DB Result",
            "type": "main",
            "index": 0
          }
        ]
      ]
    },
    "Validate DB Result": {
      "main": [
        [
          {
            "node": "Route: Success?",
            "type": "main",
            "index": 0
          }
        ]
      ]
    },
    "Route: Success?": {
      "main": [
        [
          {
            "node": "Format Output",
            "type": "main",
            "index": 0
          }
        ],
        [
          {
            "node": "Format Output",
            "type": "main",
            "index": 0
          }
        ]
      ]
    }
  },
  "settings": {
    "executionOrder": "v1",
    "saveManualExecutions": true,
    "callerPolicy": "workflowsFromSameOwner",
    "errorWorkflow": "BB_00_Global_Error_Handler"
  }
}